Workbook

Sheet Product Sales
A1: Product | B1: Quantity | C1: Price | D1: Total Amount
A2: Laptop | B2: 5 | C2: 50000 | D2: =B2*C2 -> 250000
A3: Mouse | B3: 10 | C3: 500 | D3: =B3*C3 -> 5000
A4: Keyboard | B4: 8 | C4: 1200 | D4: =B4*C4 -> 9600
A5: Monitor | B5: 4 | C5: 10000 | D5: =B5*C5 -> 40000
A6: Printer | B6: 2 | C6: 15000 | D6: =B6*C6 -> 30000
A7: Grand Total | D7: =SUM(D2:D6) -> 334600

Sheet Loan EMI Calculator
A1: Loan EMI Calculator
A2: Loan Amount | B2: 500000 | F2: Payment Component | G2: Amount
A3: Interest Rate | B3: 0.09 | F3: Principal Amount | G3: =B2 -> 500000
A4: Loan Period (Years) | B4: 5 | F4: Interest Amount | G4: =D9 -> 122750.66
B5: Monthly Interest Rate | D5: =B3/12 -> 0.0075
B6: Number of Months | D6: =B4*12 -> 60
B7: Monthly EMI | D7: =PMT(D5,D6,-B2) -> 10379.178 | F7: Loan Metric | G7: Amount
B8: Total Payment | D8: =D7*D6 -> 622750.66 | F8: Monthly EMI | G8: =D7 -> 10379.178
B9: Total Interest | D9: =D8-B2 -> 122750.66 | F9: Total Interest | G9: =D9 -> 122750.66

Sheet Chart Data
A1: Product | B1: Total Amount | D1: Payment Component | E1: Amount | G1: Loan Metric | H1: Amount
A2: Laptop | B2: ='Product Sales'!D2 -> 250000 | D2: Principal Amount | E2: ='Loan EMI Calculator'!B2 -> 500000 | G2: Monthly EMI | H2: ='Loan EMI Calculator'!D7 -> 10379.178
A3: Mouse | B3: ='Product Sales'!D3 -> 5000 | D3: Interest Amount | E3: ='Loan EMI Calculator'!D9 -> 122750.66 | G3: Total Interest | H3: ='Loan EMI Calculator'!D9 -> 122750.66
A4: Keyboard | B4: ='Product Sales'!D4 -> 9600
A5: Monitor | B5: ='Product Sales'!D5 -> 40000
A6: Printer | B6: ='Product Sales'!D6 -> 30000
